README.md
deeplator.py
setup.py
deeplator/__init__.py
deeplator/jsonrpc.py
deeplator/translator.py
deeplator.egg-info/PKG-INFO
deeplator.egg-info/SOURCES.txt
deeplator.egg-info/dependency_links.txt
deeplator.egg-info/top_level.txt