Metadata-Version: 1.2
Name: deeplator
Version: 0.0.5
Summary: Wrapper for DeepL translator.
Home-page: https://github.com/uinput/deeplator
Author: uinput
Author-email: uinput@users.noreply.github.com
License: MIT
Keywords: deepl,translation,translate,language
Platform: UNKNOWN
Classifier: Development Status :: 4 - Beta
Classifier: Intended Audience :: Developers
Classifier: License :: OSI Approved :: MIT License
Classifier: Programming Language :: Python :: 3
Requires-Python: >=3
